list/main.py
list_files_py-1.0.0.dev1.dist-info/DESCRIPTION.rst
list_files_py-1.0.0.dev1.dist-info/METADATA
list_files_py-1.0.0.dev1.dist-info/RECORD
list_files_py-1.0.0.dev1.dist-info/WHEEL
list_files_py-1.0.0.dev1.dist-info/metadata.json
list_files_py-1.0.0.dev1.dist-info/top_level.txt
